[{"operation": "Undefined", "input_shape": null, "output_shape": [1, 3, 224, 224], "node_id": "47425537639760", "connects_to": ["47425582472112"], "type": "Input", "parameters": null}, {"operation": "Conv2d", "input_shape": [[1, 3, 224, 224]], "output_shape": [[1, 64, 112, 112]], "node_id": "47425582472112", "connects_to": ["47425582121120"], "type": "Middle", "parameters": {"in_channels": 3, "out_channels": 64, "kernel_size": [7, 7], "stride": [2, 2], "padding": [3, 3], "dilation": [1, 1], "transposed": "False", "output_padding": [0, 0], "groups": 1, "padding_mode": "zeros"}}, {"operation": "BatchNorm2d", "input_shape": [[1, 64, 112, 112]], "output_shape": [[1, 64, 112, 112]], "node_id": "47425582121120", "connects_to": ["47425582121312"], "type": "Middle", "parameters": {"num_features": 64, "eps": 1e-05, "momentum": 0.1, "affine": "True", "track_running_stats": "True"}}, {"operation": "ReLU", "input_shape": [[1, 64, 112, 112]], "output_shape": [[1, 64, 112, 112]], "node_id": "47425582121312", "connects_to": ["47425582123424"], "type": "Middle", "parameters": {"inplace": "False"}}, {"operation": "MaxPool2d", "input_shape": [[1, 64, 112, 112]], "output_shape": [[1, 64, 56, 56]], "node_id": "47425582123424", "connects_to": ["47425582066416", "47425582197392"], "type": "Middle", "parameters": {"kernel_size": 3, "stride": 2, "padding": 1, "dilation": 1, "return_indices": "False", "ceil_mode": "False"}}, {"operation": "add_", "input_shape": [[1, 64, 56, 56], [1, 64, 56, 56]], "output_shape": [[1, 64, 56, 56]], "node_id": "47425582197392", "connects_to": ["47425582198352"], "type": "Middle", "parameters": null}, {"operation": "ReLU", "input_shape": [[1, 64, 56, 56]], "output_shape": [[1, 64, 56, 56]], "node_id": "47425582198352", "connects_to": ["47425582004928", "47425582004208"], "type": "Middle", "parameters": {"inplace": "False"}}, {"operation": "add_", "input_shape": [[1, 64, 56, 56], [1, 64, 56, 56]], "output_shape": [[1, 64, 56, 56]], "node_id": "47425582004208", "connects_to": ["47425602518224"], "type": "Middle", "parameters": null}, {"operation": "ReLU", "input_shape": [[1, 64, 56, 56]], "output_shape": [[1, 64, 56, 56]], "node_id": "47425602518224", "connects_to": ["47425602542512", "47425602595472"], "type": "Middle", "parameters": {"inplace": "False"}}, {"operation": "Conv2d", "input_shape": [[1, 64, 56, 56]], "output_shape": [[1, 128, 28, 28]], "node_id": "47425602542512", "connects_to": ["47425602542464"], "type": "Middle", "parameters": {"in_channels": 64, "out_channels": 128, "kernel_size": [3, 3], "stride": [2, 2], "padding": [1, 1], "dilation": [1, 1], "transposed": "False", "output_padding": [0, 0], "groups": 1, "padding_mode": "zeros"}}, {"operation": "BatchNorm2d", "input_shape": [[1, 128, 28, 28]], "output_shape": [[1, 128, 28, 28]], "node_id": "47425602542464", "connects_to": ["47425602564400"], "type": "Middle", "parameters": {"num_features": 128, "eps": 1e-05, "momentum": 0.1, "affine": "True", "track_running_stats": "True"}}, {"operation": "ReLU", "input_shape": [[1, 128, 28, 28]], "output_shape": [[1, 128, 28, 28]], "node_id": "47425602564400", "connects_to": ["47425602566992"], "type": "Middle", "parameters": {"inplace": "False"}}, {"operation": "Conv2d", "input_shape": [[1, 128, 28, 28]], "output_shape": [[1, 128, 28, 28]], "node_id": "47425602566992", "connects_to": ["47425602566896"], "type": "Middle", "parameters": {"in_channels": 128, "out_channels": 128, "kernel_size": [3, 3], "stride": [1, 1], "padding": [1, 1], "dilation": [1, 1], "transposed": "False", "output_padding": [0, 0], "groups": 1, "padding_mode": "zeros"}}, {"operation": "BatchNorm2d", "input_shape": [[1, 128, 28, 28]], "output_shape": [[1, 128, 28, 28]], "node_id": "47425602566896", "connects_to": ["47425602596144"], "type": "Middle", "parameters": {"num_features": 128, "eps": 1e-05, "momentum": 0.1, "affine": "True", "track_running_stats": "True"}}, {"operation": "add_", "input_shape": [[1, 128, 28, 28], [1, 128, 28, 28]], "output_shape": [[1, 128, 28, 28]], "node_id": "47425602596144", "connects_to": ["47425602618656"], "type": "Middle", "parameters": null}, {"operation": "ReLU", "input_shape": [[1, 128, 28, 28]], "output_shape": [[1, 128, 28, 28]], "node_id": "47425602618656", "connects_to": ["47425602642368", "47425602666752"], "type": "Middle", "parameters": {"inplace": "False"}}, {"operation": "Conv2d", "input_shape": [[1, 128, 28, 28]], "output_shape": [[1, 128, 28, 28]], "node_id": "47425602642368", "connects_to": ["47425602642272"], "type": "Middle", "parameters": {"in_channels": 128, "out_channels": 128, "kernel_size": [3, 3], "stride": [1, 1], "padding": [1, 1], "dilation": [1, 1], "transposed": "False", "output_padding": [0, 0], "groups": 1, "padding_mode": "zeros"}}, {"operation": "BatchNorm2d", "input_shape": [[1, 128, 28, 28]], "output_shape": [[1, 128, 28, 28]], "node_id": "47425602642272", "connects_to": ["47425602642992"], "type": "Middle", "parameters": {"num_features": 128, "eps": 1e-05, "momentum": 0.1, "affine": "True", "track_running_stats": "True"}}, {"operation": "ReLU", "input_shape": [[1, 128, 28, 28]], "output_shape": [[1, 128, 28, 28]], "node_id": "47425602642992", "connects_to": ["47425602666896"], "type": "Middle", "parameters": {"inplace": "False"}}, {"operation": "Conv2d", "input_shape": [[1, 128, 28, 28]], "output_shape": [[1, 128, 28, 28]], "node_id": "47425602666896", "connects_to": ["47425602666800"], "type": "Middle", "parameters": {"in_channels": 128, "out_channels": 128, "kernel_size": [3, 3], "stride": [1, 1], "padding": [1, 1], "dilation": [1, 1], "transposed": "False", "output_padding": [0, 0], "groups": 1, "padding_mode": "zeros"}}, {"operation": "BatchNorm2d", "input_shape": [[1, 128, 28, 28]], "output_shape": [[1, 128, 28, 28]], "node_id": "47425602666800", "connects_to": ["47425602666752"], "type": "Middle", "parameters": {"num_features": 128, "eps": 1e-05, "momentum": 0.1, "affine": "True", "track_running_stats": "True"}}, {"operation": "add_", "input_shape": [[1, 128, 28, 28], [1, 128, 28, 28]], "output_shape": [[1, 128, 28, 28]], "node_id": "47425602666752", "connects_to": ["47425602692048"], "type": "Middle", "parameters": null}, {"operation": "ReLU", "input_shape": [[1, 128, 28, 28]], "output_shape": [[1, 128, 28, 28]], "node_id": "47425602692048", "connects_to": ["47425602716240", "47425602765056"], "type": "Middle", "parameters": {"inplace": "False"}}, {"operation": "Conv2d", "input_shape": [[1, 128, 28, 28]], "output_shape": [[1, 256, 14, 14]], "node_id": "47425602765056", "connects_to": ["47425602764960"], "type": "Middle", "parameters": {"in_channels": 128, "out_channels": 256, "kernel_size": [1, 1], "stride": [2, 2], "padding": [0, 0], "dilation": [1, 1], "transposed": "False", "output_padding": [0, 0], "groups": 1, "padding_mode": "zeros"}}, {"operation": "BatchNorm2d", "input_shape": [[1, 256, 14, 14]], "output_shape": [[1, 256, 14, 14]], "node_id": "47425602764960", "connects_to": ["47425602765680"], "type": "Middle", "parameters": {"num_features": 256, "eps": 1e-05, "momentum": 0.1, "affine": "True", "track_running_stats": "True"}}, {"operation": "add_", "input_shape": [[1, 256, 14, 14], [1, 256, 14, 14]], "output_shape": [[1, 256, 14, 14]], "node_id": "47425602765680", "connects_to": ["47425602767648"], "type": "Middle", "parameters": null}, {"operation": "ReLU", "input_shape": [[1, 256, 14, 14]], "output_shape": [[1, 256, 14, 14]], "node_id": "47425602767648", "connects_to": ["47425602795408", "47425602794016"], "type": "Middle", "parameters": {"inplace": "False"}}, {"operation": "add_", "input_shape": [[1, 256, 14, 14], [1, 256, 14, 14]], "output_shape": [[1, 256, 14, 14]], "node_id": "47425602794016", "connects_to": ["47425602845088"], "type": "Middle", "parameters": null}, {"operation": "ReLU", "input_shape": [[1, 256, 14, 14]], "output_shape": [[1, 256, 14, 14]], "node_id": "47425602845088", "connects_to": ["47425602865184", "47425602922192"], "type": "Middle", "parameters": {"inplace": "False"}}, {"operation": "Conv2d", "input_shape": [[1, 256, 14, 14]], "output_shape": [[1, 512, 7, 7]], "node_id": "47425602865184", "connects_to": ["47425602865088"], "type": "Middle", "parameters": {"in_channels": 256, "out_channels": 512, "kernel_size": [3, 3], "stride": [2, 2], "padding": [1, 1], "dilation": [1, 1], "transposed": "False", "output_padding": [0, 0], "groups": 1, "padding_mode": "zeros"}}, {"operation": "BatchNorm2d", "input_shape": [[1, 512, 7, 7]], "output_shape": [[1, 512, 7, 7]], "node_id": "47425602865088", "connects_to": ["47425602865760"], "type": "Middle", "parameters": {"num_features": 512, "eps": 1e-05, "momentum": 0.1, "affine": "True", "track_running_stats": "True"}}, {"operation": "ReLU", "input_shape": [[1, 512, 7, 7]], "output_shape": [[1, 512, 7, 7]], "node_id": "47425602865760", "connects_to": ["47425602897856"], "type": "Middle", "parameters": {"inplace": "False"}}, {"operation": "Conv2d", "input_shape": [[1, 512, 7, 7]], "output_shape": [[1, 512, 7, 7]], "node_id": "47425602897856", "connects_to": ["47425602897760"], "type": "Middle", "parameters": {"in_channels": 512, "out_channels": 512, "kernel_size": [3, 3], "stride": [1, 1], "padding": [1, 1], "dilation": [1, 1], "transposed": "False", "output_padding": [0, 0], "groups": 1, "padding_mode": "zeros"}}, {"operation": "BatchNorm2d", "input_shape": [[1, 512, 7, 7]], "output_shape": [[1, 512, 7, 7]], "node_id": "47425602897760", "connects_to": ["47425602922816"], "type": "Middle", "parameters": {"num_features": 512, "eps": 1e-05, "momentum": 0.1, "affine": "True", "track_running_stats": "True"}}, {"operation": "add_", "input_shape": [[1, 512, 7, 7], [1, 512, 7, 7]], "output_shape": [[1, 512, 7, 7]], "node_id": "47425602922816", "connects_to": ["47425602949424"], "type": "Middle", "parameters": null}, {"operation": "ReLU", "input_shape": [[1, 512, 7, 7]], "output_shape": [[1, 512, 7, 7]], "node_id": "47425602949424", "connects_to": ["47425602952544", "47425602951104"], "type": "Middle", "parameters": {"inplace": "False"}}, {"operation": "Conv2d", "input_shape": [[1, 512, 7, 7]], "output_shape": [[1, 512, 7, 7]], "node_id": "47425602952544", "connects_to": ["47425602974336"], "type": "Middle", "parameters": {"in_channels": 512, "out_channels": 512, "kernel_size": [3, 3], "stride": [1, 1], "padding": [1, 1], "dilation": [1, 1], "transposed": "False", "output_padding": [0, 0], "groups": 1, "padding_mode": "zeros"}}, {"operation": "BatchNorm2d", "input_shape": [[1, 512, 7, 7]], "output_shape": [[1, 512, 7, 7]], "node_id": "47425602974336", "connects_to": ["47425537638992"], "type": "Middle", "parameters": {"num_features": 512, "eps": 1e-05, "momentum": 0.1, "affine": "True", "track_running_stats": "True"}}, {"operation": "ReLU", "input_shape": [[1, 512, 7, 7]], "output_shape": [[1, 512, 7, 7]], "node_id": "47425537638992", "connects_to": ["47425602975968"], "type": "Middle", "parameters": {"inplace": "False"}}, {"operation": "Conv2d", "input_shape": [[1, 512, 7, 7]], "output_shape": [[1, 512, 7, 7]], "node_id": "47425602975968", "connects_to": ["47425602975872"], "type": "Middle", "parameters": {"in_channels": 512, "out_channels": 512, "kernel_size": [3, 3], "stride": [1, 1], "padding": [1, 1], "dilation": [1, 1], "transposed": "False", "output_padding": [0, 0], "groups": 1, "padding_mode": "zeros"}}, {"operation": "BatchNorm2d", "input_shape": [[1, 512, 7, 7]], "output_shape": [[1, 512, 7, 7]], "node_id": "47425602975872", "connects_to": ["47425602951104"], "type": "Middle", "parameters": {"num_features": 512, "eps": 1e-05, "momentum": 0.1, "affine": "True", "track_running_stats": "True"}}, {"operation": "add_", "input_shape": [[1, 512, 7, 7], [1, 512, 7, 7]], "output_shape": [[1, 512, 7, 7]], "node_id": "47425602951104", "connects_to": ["47425603005216"], "type": "Middle", "parameters": null}, {"operation": "ReLU", "input_shape": [[1, 512, 7, 7]], "output_shape": [[1, 512, 7, 7]], "node_id": "47425603005216", "connects_to": ["47425582122320", "47425603032112"], "type": "Middle", "parameters": {"inplace": "False"}}, {"operation": "Undefined", "input_shape": [1, 512, 7, 7], "output_shape": null, "node_id": "47425603032112", "connects_to": [], "type": "Output", "parameters": null}, {"operation": "AdaptiveAvgPool2d", "input_shape": [[1, 512, 7, 7]], "output_shape": [[1, 512, 1, 1]], "node_id": "47425582122320", "connects_to": ["47425603031728"], "type": "Middle", "parameters": {"output_size": [1, 1]}}, {"operation": "Undefined", "input_shape": [1, 512, 1, 1], "output_shape": null, "node_id": "47425603031728", "connects_to": [], "type": "Output", "parameters": null}, {"operation": "Conv2d", "input_shape": [[1, 256, 14, 14]], "output_shape": [[1, 512, 7, 7]], "node_id": "47425602922192", "connects_to": ["47425602922096"], "type": "Middle", "parameters": {"in_channels": 256, "out_channels": 512, "kernel_size": [1, 1], "stride": [2, 2], "padding": [0, 0], "dilation": [1, 1], "transposed": "False", "output_padding": [0, 0], "groups": 1, "padding_mode": "zeros"}}, {"operation": "BatchNorm2d", "input_shape": [[1, 512, 7, 7]], "output_shape": [[1, 512, 7, 7]], "node_id": "47425602922096", "connects_to": ["47425602922816"], "type": "Middle", "parameters": {"num_features": 512, "eps": 1e-05, "momentum": 0.1, "affine": "True", "track_running_stats": "True"}}, {"operation": "Conv2d", "input_shape": [[1, 256, 14, 14]], "output_shape": [[1, 256, 14, 14]], "node_id": "47425602795408", "connects_to": ["47425602795312"], "type": "Middle", "parameters": {"in_channels": 256, "out_channels": 256, "kernel_size": [3, 3], "stride": [1, 1], "padding": [1, 1], "dilation": [1, 1], "transposed": "False", "output_padding": [0, 0], "groups": 1, "padding_mode": "zeros"}}, {"operation": "BatchNorm2d", "input_shape": [[1, 256, 14, 14]], "output_shape": [[1, 256, 14, 14]], "node_id": "47425602795312", "connects_to": ["47425602796032"], "type": "Middle", "parameters": {"num_features": 256, "eps": 1e-05, "momentum": 0.1, "affine": "True", "track_running_stats": "True"}}, {"operation": "ReLU", "input_shape": [[1, 256, 14, 14]], "output_shape": [[1, 256, 14, 14]], "node_id": "47425602796032", "connects_to": ["47425602815840"], "type": "Middle", "parameters": {"inplace": "False"}}, {"operation": "Conv2d", "input_shape": [[1, 256, 14, 14]], "output_shape": [[1, 256, 14, 14]], "node_id": "47425602815840", "connects_to": ["47425602815744"], "type": "Middle", "parameters": {"in_channels": 256, "out_channels": 256, "kernel_size": [3, 3], "stride": [1, 1], "padding": [1, 1], "dilation": [1, 1], "transposed": "False", "output_padding": [0, 0], "groups": 1, "padding_mode": "zeros"}}, {"operation": "BatchNorm2d", "input_shape": [[1, 256, 14, 14]], "output_shape": [[1, 256, 14, 14]], "node_id": "47425602815744", "connects_to": ["47425602794016"], "type": "Middle", "parameters": {"num_features": 256, "eps": 1e-05, "momentum": 0.1, "affine": "True", "track_running_stats": "True"}}, {"operation": "Conv2d", "input_shape": [[1, 128, 28, 28]], "output_shape": [[1, 256, 14, 14]], "node_id": "47425602716240", "connects_to": ["47425602716144"], "type": "Middle", "parameters": {"in_channels": 128, "out_channels": 256, "kernel_size": [3, 3], "stride": [2, 2], "padding": [1, 1], "dilation": [1, 1], "transposed": "False", "output_padding": [0, 0], "groups": 1, "padding_mode": "zeros"}}, {"operation": "BatchNorm2d", "input_shape": [[1, 256, 14, 14]], "output_shape": [[1, 256, 14, 14]], "node_id": "47425602716144", "connects_to": ["47425602716816"], "type": "Middle", "parameters": {"num_features": 256, "eps": 1e-05, "momentum": 0.1, "affine": "True", "track_running_stats": "True"}}, {"operation": "ReLU", "input_shape": [[1, 256, 14, 14]], "output_shape": [[1, 256, 14, 14]], "node_id": "47425602716816", "connects_to": ["47425602744816"], "type": "Middle", "parameters": {"inplace": "False"}}, {"operation": "Conv2d", "input_shape": [[1, 256, 14, 14]], "output_shape": [[1, 256, 14, 14]], "node_id": "47425602744816", "connects_to": ["47425602744720"], "type": "Middle", "parameters": {"in_channels": 256, "out_channels": 256, "kernel_size": [3, 3], "stride": [1, 1], "padding": [1, 1], "dilation": [1, 1], "transposed": "False", "output_padding": [0, 0], "groups": 1, "padding_mode": "zeros"}}, {"operation": "BatchNorm2d", "input_shape": [[1, 256, 14, 14]], "output_shape": [[1, 256, 14, 14]], "node_id": "47425602744720", "connects_to": ["47425602765680"], "type": "Middle", "parameters": {"num_features": 256, "eps": 1e-05, "momentum": 0.1, "affine": "True", "track_running_stats": "True"}}, {"operation": "Conv2d", "input_shape": [[1, 64, 56, 56]], "output_shape": [[1, 128, 28, 28]], "node_id": "47425602595472", "connects_to": ["47425602595376"], "type": "Middle", "parameters": {"in_channels": 64, "out_channels": 128, "kernel_size": [1, 1], "stride": [2, 2], "padding": [0, 0], "dilation": [1, 1], "transposed": "False", "output_padding": [0, 0], "groups": 1, "padding_mode": "zeros"}}, {"operation": "BatchNorm2d", "input_shape": [[1, 128, 28, 28]], "output_shape": [[1, 128, 28, 28]], "node_id": "47425602595376", "connects_to": ["47425602596144"], "type": "Middle", "parameters": {"num_features": 128, "eps": 1e-05, "momentum": 0.1, "affine": "True", "track_running_stats": "True"}}, {"operation": "Conv2d", "input_shape": [[1, 64, 56, 56]], "output_shape": [[1, 64, 56, 56]], "node_id": "47425582004928", "connects_to": ["47425582004832"], "type": "Middle", "parameters": {"in_channels": 64, "out_channels": 64, "kernel_size": [3, 3], "stride": [1, 1], "padding": [1, 1], "dilation": [1, 1], "transposed": "False", "output_padding": [0, 0], "groups": 1, "padding_mode": "zeros"}}, {"operation": "BatchNorm2d", "input_shape": [[1, 64, 56, 56]], "output_shape": [[1, 64, 56, 56]], "node_id": "47425582004832", "connects_to": ["47425581970528"], "type": "Middle", "parameters": {"num_features": 64, "eps": 1e-05, "momentum": 0.1, "affine": "True", "track_running_stats": "True"}}, {"operation": "ReLU", "input_shape": [[1, 64, 56, 56]], "output_shape": [[1, 64, 56, 56]], "node_id": "47425581970528", "connects_to": ["47425581972112"], "type": "Middle", "parameters": {"inplace": "False"}}, {"operation": "Conv2d", "input_shape": [[1, 64, 56, 56]], "output_shape": [[1, 64, 56, 56]], "node_id": "47425581972112", "connects_to": ["47425581972016"], "type": "Middle", "parameters": {"in_channels": 64, "out_channels": 64, "kernel_size": [3, 3], "stride": [1, 1], "padding": [1, 1], "dilation": [1, 1], "transposed": "False", "output_padding": [0, 0], "groups": 1, "padding_mode": "zeros"}}, {"operation": "BatchNorm2d", "input_shape": [[1, 64, 56, 56]], "output_shape": [[1, 64, 56, 56]], "node_id": "47425581972016", "connects_to": ["47425582004208"], "type": "Middle", "parameters": {"num_features": 64, "eps": 1e-05, "momentum": 0.1, "affine": "True", "track_running_stats": "True"}}, {"operation": "Conv2d", "input_shape": [[1, 64, 56, 56]], "output_shape": [[1, 64, 56, 56]], "node_id": "47425582066416", "connects_to": ["47425582035200"], "type": "Middle", "parameters": {"in_channels": 64, "out_channels": 64, "kernel_size": [3, 3], "stride": [1, 1], "padding": [1, 1], "dilation": [1, 1], "transposed": "False", "output_padding": [0, 0], "groups": 1, "padding_mode": "zeros"}}, {"operation": "BatchNorm2d", "input_shape": [[1, 64, 56, 56]], "output_shape": [[1, 64, 56, 56]], "node_id": "47425582035200", "connects_to": ["47425582035392"], "type": "Middle", "parameters": {"num_features": 64, "eps": 1e-05, "momentum": 0.1, "affine": "True", "track_running_stats": "True"}}, {"operation": "ReLU", "input_shape": [[1, 64, 56, 56]], "output_shape": [[1, 64, 56, 56]], "node_id": "47425582035392", "connects_to": ["47425582038032"], "type": "Middle", "parameters": {"inplace": "False"}}, {"operation": "Conv2d", "input_shape": [[1, 64, 56, 56]], "output_shape": [[1, 64, 56, 56]], "node_id": "47425582038032", "connects_to": ["47425582194944"], "type": "Middle", "parameters": {"in_channels": 64, "out_channels": 64, "kernel_size": [3, 3], "stride": [1, 1], "padding": [1, 1], "dilation": [1, 1], "transposed": "False", "output_padding": [0, 0], "groups": 1, "padding_mode": "zeros"}}, {"operation": "BatchNorm2d", "input_shape": [[1, 64, 56, 56]], "output_shape": [[1, 64, 56, 56]], "node_id": "47425582194944", "connects_to": ["47425582197392"], "type": "Middle", "parameters": {"num_features": 64, "eps": 1e-05, "momentum": 0.1, "affine": "True", "track_running_stats": "True"}}]